{
    "name": "Nui-Track RealSense Data",
    "date": "2019-07-16T17:02:14.7433536+02:00",
    "format": {
            "LeftWrist": 0,
            "LeftElbow": 1,
            "LeftShoulder": 2,
            "Neck": 3,
            "Torso": 4,
            "Waist": 5,
            "LeftAnkle": 6,
            "LeftKnee": 7,
            "LeftHip": 8,
            "RightAnkle": 9,
            "RightKnee": 10,
            "RightHip": 11,
            "RightWrist": 12,
            "RightElbow": 13,
            "RightShoulder": 14,
            "Head": 15
        },
    "timestamps": [
        0.33
    ],
    "frames": [
        [
            -0.2719878,
            -0.101372778,
            1.6825006,
            -0.254942626,
            0.1692208,
            1.747616,
            -0.190284491,
            0.461070776,
            1.7138226,
            -0.0106640523,
            0.5603107,
            1.6993804,
            0.00100231939,
            0.1807794,
            1.69604647,
            0.00766339,
            -0.0249372572,
            1.67607713,
            -0.0529203862,
            -0.9635677,
            1.5088675,
            -0.0529203862,
            -0.5342281,
            1.5088675,
            -0.107149519,
            -0.124244213,
            1.70838737,
            0.0362705924,
            -0.981947,
            1.699688,
            0.09259366,
            -0.5645316,
            1.61647379,
            0.131936982,
            -0.114628732,
            1.69939065,
            0.3304197,
            -0.08476123,
            1.68040454,
            0.232941464,
            0.168404415,
            1.74487615,
            0.166854143,
            0.4567532,
            1.69022715,
            -0.016861897,
            0.6854695,
            1.73485112
        ]
    ]
}